{
  "key": "application",
  "content": {
    "nav": {
      "home": "หน้าแรก",
      "downloads": "ดาวน์โหลด",
      "docs": "เอกสาร",
      "api": "API"
    },
    "hero": {
      "versionBadge": "✨ เวอร์ชั่นใหม่ล่าสุด v0.9.2 ✨",
      "welcome": "ยินดีต้อนรับสู่",
      "future": "อนาคต",
      "description": "ค้นพบโปรแกรมที่จะปฏิวัติการทำงานของคุณด้วยเทคโนโลยีล้ำสมัยและประสิทธิภาพสูงสุด",
      "downloadButton": "ดาวน์โหลด",
      "howToUseButton": "วิธีใช้งาน"
    },
    "techStack": {
      "title": "เทคโนโลยีที่ใช้"
    },
    "search": {
      "title": "ค้นหาทุกอย่างได้อย่างรวดเร็ว",
      "placeholder": "ค้นหาคอนเทนท์ที่ต้องการ...",
      "description": "เชื่อมต่อกับระบบ search engine ประสิทธิภาพสูง"
    },
    "cta": {
      "title": "เริ่มต้นใช้งานวันนี้",
      "description": "ดาวน์โหลดและติดตั้งแอพพลิเคชันฟรี",
      "windows": "วินโดวส์",
      "macos": "แมคโอเอส",
      "linux": "ลินุกซ์"
    },
    "footer": {
      "copyright": "© 2568 ChanomHub. สงวนลิขสิทธิ์ทั้งหมด"
    },
    "features": {
      "lightningFast": {
        "title": "รวดเร็วปานสายฟ้า",
        "description": "สร้างด้วย Rust และ Tauri เพื่อประสิทธิภาพสูงสุด"
      },
      "secureReliable": {
        "title": "ปลอดภัยและเชื่อถือได้",
        "description": "ความปลอดภัยระดับองค์กรพร้อมอัปเดตต่อเนื่อง"
      },
      "developerFriendly": {
        "title": "เป็นมิตรกับนักพัฒนา",
        "description": "API ที่สะอาดและเอกสารที่ครอบคลุม"
      }
    },
    "themeSelector": {
      "title": "เลือกธีมที่ใช่สำหรับคุณ",
      "description": "ปรับแต่งแอพพลิเคชันให้เข้ากับสไตล์ของคุณ",
      "themes": {
        "cyber": "ไซเบอร์",
        "neon": "นีออน",
        "matrix": "เมทริกซ์",
        "sunset": "พระอาทิตย์ตก",
        "arctic": "อาร์กติก"
      }
    }
  },
  "locale": "th"
}